<laserDevice>
  <jobSentText>Job was sent. Press the joystick on the lasercutter.</jobSentText>
  <jobPrefix>visicut </jobPrefix>
  <laserCutter class="com.t_oster.liblasercut.drivers.LaosCutter">
    <supportsFrequency>false</supportsFrequency>
    <supportsFocus>false</supportsFocus>
    <supportsPurge>false</supportsPurge>
    <supportsVentilation>false</supportsVentilation>
    <debugFilename></debugFilename>
    <addSpacePerRasterLine>20.0</addSpacePerRasterLine>
    <useTftp>true</useTftp>
    <flipXaxis>false</flipXaxis>
    <flipYaxis>true</flipYaxis>
    <hostname>10.0.0.16</hostname>
    <port>69</port>
    <mmPerStep>0.0010</mmPerStep>
    <currentPower>-1.0</currentPower>
    <currentSpeed>-1.0</currentSpeed>
    <currentFrequency>-1</currentFrequency>
    <currentFocus>0.0</currentFocus>
    <bedWidth>520.0</bedWidth>
    <bedHeight>330.0</bedHeight>
  </laserCutter>
  <cameraCalibration serialization="custom">
    <java.awt.geom.AffineTransform>
      <default>
        <m00>0.5370051635111877</m00>
        <m01>0.0</m01>
        <m02>-87.71084337349399</m02>
        <m10>0.0</m10>
        <m11>0.5308310991957105</m11>
        <m12>-128.28418230563003</m12>
      </default>
    </java.awt.geom.AffineTransform>
  </cameraCalibration>
  <cameraURL>http://10.0.0.34:8081/?action=snapshot</cameraURL>
  <thumbnailPath>Big_32_lasercutter.png</thumbnailPath>
  <name>Big lasercutter</name>
</laserDevice>